LICENSE
README.md
setup.py
criptografiaferik/__init__.py
criptografiaferik/demo.py
criptografiaferik/main.py
criptografiaferik.egg-info/PKG-INFO
criptografiaferik.egg-info/SOURCES.txt
criptografiaferik.egg-info/dependency_links.txt
criptografiaferik.egg-info/requires.txt
criptografiaferik.egg-info/top_level.txt