Metadata-Version: 2.1
Name: criptografiaferik
Version: 0.5
Summary: Uma biblioteca para criptografia de mensagens
Home-page: https://github.com/eriksoaress/Criptografia
Author: Erik Soares e Fernando Santos
Classifier: Development Status :: 3 - Alpha
Classifier: Intended Audience :: Developers
Classifier: License :: OSI Approved :: MIT License
Classifier: Programming Language :: Python :: 3
Classifier: Programming Language :: Python :: 3.6
Classifier: Programming Language :: Python :: 3.7
Classifier: Programming Language :: Python :: 3.8
License-File: LICENSE
